xpath_kit-0.4.0.dist-info/licenses/LICENCE
xpathkit/__init__.py
xpathkit/__version__.py
xpathkit/builders.py
xpathkit/exceptions.py
xpathkit/expressions.py
xpathkit/xpathkit.py
xpath_kit-0.4.0.dist-info/METADATA
xpath_kit-0.4.0.dist-info/WHEEL
xpath_kit-0.4.0.dist-info/top_level.txt
xpath_kit-0.4.0.dist-info/RECORD
