Metadata-Version: 2.4
Name: xpath-kit
Version: 0.4.0
Summary: A toolkit for convenient and expressive XPath operations based on lxml.
Author-email: Kabxx <2201174299@qq.com>
Keywords: xpath,lxml,xml,html,parser
Classifier: Programming Language :: Python :: 3
Classifier: License :: OSI Approved :: MIT License
Classifier: Operating System :: OS Independent
Classifier: Development Status :: 3 - Alpha
Classifier: Intended Audience :: Developers
Classifier: Topic :: Software Development :: Libraries :: Python Modules
Requires-Python: >=3.12
License-File: LICENCE
Requires-Dist: lxml>=6.0.0
Provides-Extra: test
Requires-Dist: pytest; extra == "test"
Dynamic: license-file
